algoliasearchasync/__init__.py
algoliasearchasync/client.py
algoliasearchasync/helpers.py
algoliasearchasync/index.py
algoliasearchasync/transport.py
algoliasearchasync/version.py
algoliasearchasync-1.3.2.dist-info/DESCRIPTION.rst
algoliasearchasync-1.3.2.dist-info/METADATA
algoliasearchasync-1.3.2.dist-info/RECORD
algoliasearchasync-1.3.2.dist-info/WHEEL
algoliasearchasync-1.3.2.dist-info/metadata.json
algoliasearchasync-1.3.2.dist-info/top_level.txt
