Metadata-Version: 2.0
Name: algoliasearchasync
Version: 1.3.2
Summary: Algolia Search Asyncronous API Client for Python
Home-page: https://github.com/algolia/algoliasearch-client-python-async
Author: Algolia Team
Author-email: support@algolia.com
License: MIT License
Keywords: algolia,pyalgolia,search,backend,hosted,cloud,full-text search,faceted search,async
Platform: UNKNOWN
Classifier: Intended Audience :: Developers
Classifier: License :: OSI Approved :: MIT License
Classifier: Operating System :: OS Independent
Classifier: Programming Language :: Python
Classifier: Programming Language :: Python :: 3.4
Classifier: Programming Language :: Python :: 3.5
Classifier: Topic :: Internet
Classifier: Topic :: Internet :: WWW/HTTP
Classifier: Topic :: Internet :: WWW/HTTP :: Indexing/Search
Classifier: Development Status :: 4 - Beta
Requires-Dist: algoliasearch (>=1.10.1)
Requires-Dist: aiohttp (>=2.0.5)
